pixoo/__init__.py
pixoo/utilities.py
pixoo/configurations/__init__.py
pixoo/configurations/pixooconfiguration.py
pixoo/configurations/restconfiguration.py
pixoo/configurations/simulatorconfiguration.py
pixoo/constants/__init__.py
pixoo/constants/colors.py
pixoo/constants/font.py
pixoo/enums/__init__.py
pixoo/enums/channel.py
pixoo/enums/imageresamplemode.py
pixoo/enums/textscrolldirection.py
pixoo/objects/__init__.py
pixoo/objects/pixoo.py
pixoo/objects/pixoorest.py
pixoo/objects/simulator.py
pixoo-0.9.2.dist-info/LICENSE
pixoo-0.9.2.dist-info/METADATA
pixoo-0.9.2.dist-info/WHEEL
pixoo-0.9.2.dist-info/top_level.txt
pixoo-0.9.2.dist-info/RECORD
