Metadata-Version: 2.1
Name: pixoo
Version: 0.9.2
Summary: A library to easily communicate with the Divoom Pixoo 64
Home-page: https://github.com/SomethingWithComputers/pixoo#readme
Author: Ron Talman
Author-email: Ron Talman <ron@somethingwithcomputers.com>
License: Attribution-NonCommercial-ShareAlike 4.0 International
Project-URL: Homepage, https://github.com/SomethingWithComputers/pixoo
Project-URL: Issues, https://github.com/SomethingWithComputers/pixoo/issues
Keywords: pixoo,divoom,pixoo64
Classifier: Programming Language :: Python :: 3
Classifier: Operating System :: OS Independent
Requires-Python: >=3.10
License-File: LICENSE
Requires-Dist: Flask~=3.0.3
Requires-Dist: requests~=2.32.3
Requires-Dist: pillow~=10.4.0
